package/__init__.py
package/cache.py
package/utils.py
cimdem_test_package-0.1.dist-info/METADATA
cimdem_test_package-0.1.dist-info/WHEEL
cimdem_test_package-0.1.dist-info/top_level.txt
cimdem_test_package-0.1.dist-info/RECORD
