Metadata-Version: 2.1
Name: cimdem_test_package
Version: 0.1
Summary: A short description of your package
Home-page: https://github.com/yourusername/mypackage
Author: Your Name
Author-email: your.email@example.com
Requires-Dist: aiohttp ~=3.9.4
Requires-Dist: backoff ~=2.2.1
Requires-Dist: coverage ~=6.4.3
Requires-Dist: cryptography ~=42.0.4
Requires-Dist: geojson ~=3.0.1
Requires-Dist: mock ~=4.0.3
Requires-Dist: nltk ~=3.7
Requires-Dist: numpy <=1.21,>=1.20
Requires-Dist: numba
Requires-Dist: pandarallel ~=1.6.4
Requires-Dist: pandas >=1.4.1
Requires-Dist: psutil ~=5.9.4
Requires-Dist: pygeocodio >=1.0.0
Requires-Dist: pytest ~=7.1.1
Requires-Dist: pytest-asyncio ~=0.23.3
Requires-Dist: regex ~=2022.7.9
Requires-Dist: requests ~=2.31.0
Requires-Dist: schemachange >=3.5.2
Requires-Dist: setuptools >=65.5.1
Requires-Dist: shapely ~=2.0.1
Requires-Dist: snowflake-connector-python[pandas] >=3.1.0
Requires-Dist: timeout-decorator ~=0.5.0
Requires-Dist: urllib3 ~=1.26.8
Requires-Dist: usaddress ~=0.5.10
Requires-Dist: python-dotenv >=0.20.0
Requires-Dist: pytest-mock ~=3.8.2
Requires-Dist: python-json-logger
